mox/__init__.py
mox/comparators.py
mox/contextmanagers.py
mox/exceptions.py
mox/groups.py
mox/helpers.py
mox/mox.py
mox/stubbingout.py
mox/testing/__init__.py
mox/testing/pytest_mox.py
mox/testing/unittest_mox.py
pymox-1.4.0.dist-info/COPYING
pymox-1.4.0.dist-info/METADATA
pymox-1.4.0.dist-info/WHEEL
pymox-1.4.0.dist-info/RECORD
