Metadata-Version: 2.1
Name: pymox
Version: 1.4.0
Summary: Mock object framework
Home-page: http://pymox.rtfd.io
License: Apache License, Version 2.0
Keywords: mox,mock,test,mocking,unittest,pymox
Author: Ivan Neto
Author-email: ivan.cr.neto@gmail.com
Requires-Python: >=3.8,<4
Classifier: Development Status :: 5 - Production/Stable
Classifier: Environment :: Console
Classifier: Framework :: Pytest
Classifier: Intended Audience :: Developers
Classifier: License :: OSI Approved :: Apache Software License
Classifier: License :: Other/Proprietary License
Classifier: Operating System :: OS Independent
Classifier: Programming Language :: Python
Classifier: Programming Language :: Python :: 3
Classifier: Programming Language :: Python :: 3.8
Classifier: Programming Language :: Python :: 3.9
Classifier: Programming Language :: Python :: 3.10
Classifier: Programming Language :: Python :: 3.11
Classifier: Programming Language :: Python :: 3.12
Classifier: Programming Language :: Python :: Implementation :: CPython
Classifier: Programming Language :: Python :: Implementation :: PyPy
Classifier: Topic :: Software Development :: Quality Assurance
Classifier: Topic :: Software Development :: Testing
Classifier: Topic :: Utilities
Requires-Dist: build (>=1.0.3,<2.0.0)
Requires-Dist: setuptools_scm (>=8.0,<9.0) ; python_version >= "3.8" and python_version < "4"
Project-URL: Repository, https://github.com/ivancrneto/pymox
